pyThermoLinkDB/__init__.py
pyThermoLinkDB/app.py
pyThermoLinkDB/config/__init__.py
pyThermoLinkDB/config/constants.py
pyThermoLinkDB/config/deps.py
pyThermoLinkDB/config/settings.py
pyThermoLinkDB/docs/__init__.py
pyThermoLinkDB/docs/thermodbhub.py
pyThermoLinkDB/docs/thermolink.py
pyThermoLinkDB/docs/utils.py
pyThermoLinkDB/models/__init__.py
pyThermoLinkDB/models/component_models.py
pyThermoLinkDB/models/ref.py
pyThermoLinkDB/models/source.py
pyThermoLinkDB/thermo/__init__.py
pyThermoLinkDB/thermo/data_source.py
pyThermoLinkDB/thermo/equation_source.py
pyThermoLinkDB/thermo/equation_sources.py
pyThermoLinkDB/thermo/main.py
pyThermoLinkDB/thermo/source.py
pyThermoLinkDB/utils/__init__.py
pyThermoLinkDB/utils/convertor.py
pyThermoLinkDB/utils/loader.py
pyThermoLinkDB/utils/properties.py
pythermolinkdb-1.4.9.dist-info/licenses/LICENSE
pythermolinkdb-1.4.9.dist-info/METADATA
pythermolinkdb-1.4.9.dist-info/WHEEL
pythermolinkdb-1.4.9.dist-info/top_level.txt
pythermolinkdb-1.4.9.dist-info/RECORD
