Metadata-Version: 2.4
Name: PyThermoLinkDB
Version: 1.4.9
Summary: PyThermoLinkDB is a Python package providing a robust and efficient interface between `PyThermoDB` and other applications.
Author-email: Sina Gilassi <sina.gilassi@gmail.com>
License-Expression: MIT
Project-URL: Homepage, https://github.com/sinagilassi/PyThermoLinkDB
Project-URL: Documentation, https://pythermolinkdb.readthedocs.io/en/latest/
Project-URL: Source, https://github.com/sinagilassi/PyThermoLinkDB
Project-URL: Issue Tracker, https://github.com/sinagilassi/PyThermoLinkDB/issues
Keywords: chemical engineering,thermodynamics,PyThermoDB
Classifier: Development Status :: 1 - Planning
Classifier: Intended Audience :: Education
Classifier: Programming Language :: Python :: 3.11
Classifier: Operating System :: Unix
Classifier: Operating System :: MacOS :: MacOS X
Classifier: Operating System :: Microsoft :: Windows
Requires-Python: >=3.11
License-File: LICENSE
Requires-Dist: pyyaml>=6.0.2
Requires-Dist: pydantic>=2.11.7
Requires-Dist: pydantic-settings>=2.10.1
Requires-Dist: pythermodb
Requires-Dist: pythermodb-settings
Provides-Extra: dev
Requires-Dist: rich>=14.2.0; extra == "dev"
Dynamic: license-file
